Metadata-Version: 2.1
Name: GSMEncoding
Version: 0.0.2
Summary:  This package implements encode/decode functions for GSM (SMS). 
Home-page: https://github.com/mauricelambert/GSMEncoding
Author: Maurice Lambert
Author-email: mauricelambert434@gmail.com
Maintainer: Maurice Lambert
Maintainer-email: mauricelambert434@gmail.com
License: GPL-3.0 License
Project-URL: Documentation, https://mauricelambert.github.io/info/python/code/GSMEncoding.html
Keywords: GSM,SMS,Encoding
Platform: Windows
Platform: Linux
Platform: MacOS
Classifier: Programming Language :: Python
Classifier: Development Status :: 5 - Production/Stable
Classifier: Topic :: Communications
Classifier: Natural Language :: English
Classifier: Programming Language :: Python :: 3.9
Classifier: Operating System :: POSIX :: Linux
Classifier: Operating System :: Microsoft :: Windows
Classifier: Operating System :: MacOS
Requires-Python: >=3.6
License-File: LICENSE.txt
